examples/counter/cells_sim.v
// Behavioral models for the counter's gate cells, so the gate-level netlist
// (counter.v) is simulatable by Verilator to emit a SAIF over its REAL nets
// (clk, n0, y, q0, q1) via --trace-saif. For activity generation only — these
// are simulation stand-ins, not the characterized cells in counter.lib.
module CLKBUF (input A, output X); assign X = A; endmodule
module BUF    (input A, output Y); assign Y = A; endmodule
module INV    (input A, output Y); assign Y = ~A; endmodule
module DFF    (input CK, input D, output reg Q);
  initial Q = 1'b0;
  always @(posedge CK) Q <= D;
endmodule

examples/counter/counter.v
// Gate-level counter matching examples/counter/counter.def — the same instances
// (clkbuf, ff0, ff1, u0, u1) and the nets clk + n0 that vyges-extract extracts,
// so clkbuf's output net (clk) and u0's output net (n0) get REAL extracted wire
// caps from counter.spef; the other output nets fall back to the stand-in.
module counter (clk_in, d, q0, q1, y);
  input  clk_in, d;
  output q0, q1, y;
  wire clk, n0;
  CLKBUF clkbuf (.A(clk_in), .X(clk));     // drives net clk  (SPEF: 0.4565 fF)
  INV    u0     (.A(d),      .Y(n0));       // drives net n0   (SPEF: 0.0869 fF)
  BUF    u1     (.A(n0),     .Y(y));
  DFF    ff0    (.CK(clk),   .D(d),  .Q(q0));
  DFF    ff1    (.CK(clk),   .D(n0), .Q(q1));
endmodule

examples/counter/counter.vcd
$timescale 1ns $end
$scope module counter $end
$var wire 1 ! clk_in $end
$var wire 1 @ clk $end
$var wire 1 # d $end
$var wire 1 % n0 $end
$var wire 1 & y $end
$var wire 1 ( q0 $end
$var wire 1 ) q1 $end
$upscope $end
$enddefinitions $end
$dumpvars
0!
0@
0#
1%
0&
0(
0)
$end
#5
1!
1@
#10
0!
0@
1#
0%
#15
1!
1@
1&
#20
0!
0@
1(
#25
1!
1@
0#
1%
#30
0!
0@
0&
#35
1!
1@
1)
0(
#40
0!
0@
0%
#45
1!
1@
1&
